fencer/__init__.py
fencer/api_spec.py
fencer/authorized_endpoints.py
fencer/cli.py
fencer/jwts.py
fencer/mass_assignment.py
fencer/openapi.json
fencer/payload_size.py
fencer/query_params.py
fencer/rate_limiting.py
fencer/sql_injection.py
fencer/surface_attack.py
fencer/test_case.py
fencer/test_runner.py
fencer/url_path_params.py
fencer/user_restricted_access.py
fencer-0.3.6.dist-info/METADATA
fencer-0.3.6.dist-info/WHEEL
fencer-0.3.6.dist-info/entry_points.txt
fencer-0.3.6.dist-info/licenses/LICENSE
fencer-0.3.6.dist-info/RECORD
