Metadata-Version: 2.1
Name: fencer
Version: 0.3.6
Summary: Automated API security testing.
Project-URL: Homepage, https://github.com/abunuwas/fencer
Project-URL: Source, https://github.com/abunuwas/fencer
Project-URL: Changelog, https://github.com/abunuwas/fencer/blob/main/CHANGES.md
Project-URL: Bug Tracker, https://github.com/abunuwas/fencer/issues
Author-email: José Haro Peralta <jose@microapis.io>
License-Expression: MIT
License-File: LICENSE
Classifier: Development Status :: 2 - Pre-Alpha
Classifier: Environment :: Console
Classifier: Intended Audience :: Developers
Classifier: License :: OSI Approved :: MIT License
Classifier: Operating System :: OS Independent
Classifier: Programming Language :: Python
Classifier: Programming Language :: Python :: 3 :: Only
Classifier: Programming Language :: Python :: 3.10
Classifier: Programming Language :: Python :: 3.11
Classifier: Topic :: Software Development :: Libraries :: Python Modules
Classifier: Topic :: Software Development :: Quality Assurance
Requires-Python: >=3.7
Requires-Dist: click>=8.0.0
Requires-Dist: exrex>=0.10.5
Requires-Dist: jsf>=0.7.1
Requires-Dist: pyyaml>=0.6
Requires-Dist: requests>=2.28.2
Requires-Dist: tabulate>=0.9.0
